<?xml version="1.0" encoding="utf-8"?>
<DeliveryManDB xmlns:xsi="http://www.w3.org/2001/XMLSchema-instance" xmlns:xsd="http://www.w3.org/2001/XMLSchema">
  <ListDB>
    <DeliveryMan>
      <Status>0</Status>
      <Address>asdasd</Address>
      <Category>Repartidor</Category>
      <Email>asasda</Email>
      <PhoneNumber>1234</PhoneNumber>
      <DocumentNumber>1234</DocumentNumber>
      <Gender>77</Gender>
      <LastName>as</LastName>
      <FirstName>as</FirstName>
      <Password>1234</Password>
      <Username>Repartidor</Username>
      <Id>1</Id>
      <VerificationCode>123456</VerificationCode>
      <Salary>0</Salary>
      <Available>false</Available>
      <Quota>0</Quota>
    </DeliveryMan>
  </ListDB>
</DeliveryManDB>