<?xml version="1.0" encoding="utf-8"?>
<ManagerDB xmlns:xsd="http://www.w3.org/2001/XMLSchema" xmlns:xsi="http://www.w3.org/2001/XMLSchema-instance">
  <ListDB>
    <Manager>
      <Status>0</Status>
      <Address>Lima Norte</Address>
      <Category>Manager</Category>
      <Email>piero@hotmail.com</Email>
      <PhoneNumber>456123</PhoneNumber>
      <DocumentNumber>7894662</DocumentNumber>
      <Gender>77</Gender>
      <LastName>Sánchez</LastName>
      <FirstName>Piero</FirstName>
      <Password>1234</Password>
      <Username>jefecito</Username>
      <Id>9</Id>
      <VerificationCode>0</VerificationCode>
      <Salary>0</Salary>
      <EmployeesNumber>0</EmployeesNumber>
    </Manager>
  </ListDB>
</ManagerDB>